cryptoshredding/__init__.py
cryptoshredding/dynamodb_key_store.py
cryptoshredding/exceptions.py
cryptoshredding/in_memory_key_store.py
cryptoshredding/key_store.py
cryptoshredding/main_key.py
cryptoshredding/dynamodb/__init__.py
cryptoshredding/dynamodb/client.py
cryptoshredding/dynamodb/item.py
cryptoshredding/dynamodb/materials_provider.py
cryptoshredding/dynamodb/resource.py
cryptoshredding/dynamodb/table.py
cryptoshredding/kinesis/__init__.py
cryptoshredding/kinesis/client.py
cryptoshredding/raw/__init__.py
cryptoshredding/raw/bytes.py
cryptoshredding/raw/file.py
cryptoshredding/raw/key_provider.py
cryptoshredding/raw/string.py
cryptoshredding/s3/__init__.py
cryptoshredding/s3/bucket.py
cryptoshredding/s3/client.py
cryptoshredding/s3/object.py
cryptoshredding/s3/stream_body_wrapper.py
cryptoshredding-0.0.4.data/data/LICENSE
cryptoshredding-0.0.4.data/data/README.rst
cryptoshredding-0.0.4.dist-info/LICENSE
cryptoshredding-0.0.4.dist-info/METADATA
cryptoshredding-0.0.4.dist-info/WHEEL
cryptoshredding-0.0.4.dist-info/top_level.txt
cryptoshredding-0.0.4.dist-info/RECORD
