Metadata-Version: 2.1
Name: cryptoshredding
Version: 0.0.4
Summary: Crypto shredding for Python
Home-page: https://github.com/hupe1980/cryptoshredding
Author: hupe1980
License: MIT
Keywords: cryptoshredding gdpr aws kms client-side-encryption dynamodb s3
Platform: UNKNOWN
Classifier: Development Status :: 3 - Alpha
Classifier: Intended Audience :: Developers
Classifier: Natural Language :: English
Classifier: License :: OSI Approved :: MIT License
Classifier: Programming Language :: Python
Classifier: Programming Language :: Python :: 3.6
Classifier: Programming Language :: Python :: 3.7
Classifier: Programming Language :: Python :: 3.8
Classifier: Programming Language :: Python :: 3.9
Classifier: Topic :: Security
Classifier: Topic :: Security :: Cryptography
Requires-Python: >= 3.6
Requires-Dist: aws-encryption-sdk (>=2.0.0)
Requires-Dist: boto3 (>=1.16.63)
Requires-Dist: cryptography (>=3.3.1)
Requires-Dist: dynamodb-encryption-sdk (>=2.0.0)
Requires-Dist: SQLAlchemy (>=1.3.23)
Requires-Dist: pymongo (>=3.11.3)
